pylabels/__init__.py
pylabels/build_label_def.py
pylabels/build_spec.py
pylabels/constants.py
pylabels/sheet.py
pylabels/specifications.py
pylabels/demos/Judson-Bold.ttf
pylabels/demos/KatamotzIkasi.ttf
pylabels/demos/address_label.py
pylabels/demos/addresses.csv
pylabels/demos/addresses.py
pylabels/demos/background_colours.py
pylabels/demos/basic.py
pylabels/demos/labeldef.json
pylabels/demos/labeldef.py
pylabels/demos/names.txt
pylabels/demos/nametags.py
pylabels/demos/padding.py
pylabels/demos/page_background.py
pylabels/demos/page_background_1.png
pylabels/demos/page_background_2.png
pylabels/demos/partial_page.py
pylabels/demos/preview.py
pylabels/demos/qr.py
pylabels/demos/repeated.py
pylabels/demos/django_demo/README.md
pylabels/demos/django_demo/project/manage.py
pylabels/demos/django_demo/project/barcode_app/__init__.py
pylabels/demos/django_demo/project/barcode_app/admin.py
pylabels/demos/django_demo/project/barcode_app/apps.py
pylabels/demos/django_demo/project/barcode_app/barcode.py
pylabels/demos/django_demo/project/barcode_app/models.py
pylabels/demos/django_demo/project/barcode_app/views.py
pylabels/demos/django_demo/project/barcode_app/management/commands/__init__.py
pylabels/demos/django_demo/project/barcode_app/management/commands/prepare.py
pylabels/demos/django_demo/project/barcode_app/migrations/0001_initial.py
pylabels/demos/django_demo/project/barcode_app/migrations/__init__.py
pylabels/demos/django_demo/project/barcode_app/static/css/barcode.css
pylabels/demos/django_demo/project/barcode_app/static/css/navbar.css
pylabels/demos/django_demo/project/barcode_app/templates/home.html
pylabels/demos/django_demo/project/barcode_app/templates/navbar.html
pylabels/demos/django_demo/project/project/__init__.py
pylabels/demos/django_demo/project/project/settings.py
pylabels/demos/django_demo/project/project/urls.py
pylabels/demos/django_demo/project/project/wsgi.py
pylabels/predefined/__init__.py
pylabels/predefined/__main__.py
pylabels2-1.4.4.dist-info/LICENSE
pylabels2-1.4.4.dist-info/METADATA
pylabels2-1.4.4.dist-info/WHEEL
pylabels2-1.4.4.dist-info/top_level.txt
pylabels2-1.4.4.dist-info/RECORD
