Metadata-Version: 2.1
Name: pylabels2
Version: 1.4.4
Summary: Library to generate PDFs for printing labels
Author: Blair Bonnett
License:                     GNU GENERAL PUBLIC LICENSE
Keywords: labels avery
Classifier: Development Status :: 5 - Production/Stable
Classifier: License :: OSI Approved :: GNU General Public License v3 or later (GPLv3+)
Classifier: Operating System :: OS Independent
Classifier: Programming Language :: Python
Requires-Python: >=3.12
License-File: LICENSE
Requires-Dist: reportlab
